cardsec/.gitignore
cardsec/main.py
cardsec/port_scanner.py
cardsec/utils.py
cardsec-0.2.1.dist-info/entry_points.txt
cardsec-0.2.1.dist-info/LICENSE.md
cardsec-0.2.1.dist-info/WHEEL
cardsec-0.2.1.dist-info/METADATA
cardsec-0.2.1.dist-info/RECORD
